[
    {
        "key": 1,
        "course": "English courses for children aged 6–17",
        "img": "https://thumbs.dreamstime.com/z/english-kids-vector-illustration-two-kids-learning-english-language-school-children-studying-foreign-languages-72344335.jpg",
        "description": "Discover our English courses for children: Primary Plus for ages 6–12 and Secondary Plus for ages 12–17.",
        "duration": 6,
        "cost":20
    },
    {
        "key": 2,
        "course": "Grammar and vocabulary courses",
        "img": "https://cdn.slidesharecdn.com/ss_thumbnails/howtoteachgrammartokids-150105041054-conversion-gate02-thumbnail-4.jpg?cb=1420431282",
        "description": "lively classes with a specialist teacher, who will encourage their curiosity and keep them motivated to practise speaking English",
        "duration": 3,
        "cost":30
    },
    {
        "key": 3,
        "course": "Online English courses for you",
        "img": "https://encrypted-tbn0.gstatic.com/images?q=tbn:ANd9GcSDCYPf_fG5Jze9sLPCbHyUQKG-4qDDXe2vWspotDd64WzSndBkTnGgH8vaS5-SnPi8kSk&usqp=CAU",
        "description": "Our classes focus on practical skills and interactive exercises. Each module is brought to life with activities",
        "duration": 2,
        "cost":25
    },
    {
        "key": 4,
        "course": "Fun and Learn English",
        "img": "https://encrypted-tbn0.gstatic.com/images?q=tbn:ANd9GcRDRn5PL2yZ5Z4_ZZ6MQ7ELUehCJGfgwnCPZPKZDHHi8DVlnVbMOgspOnnqwvM182vsgLA&usqp=CAU",
        "description": "At home your child will improve their language skills with engaging, high-quality online learning resources.",
        "duration": 5,
        "cost":22
    },
    {
        "key": 5,
        "course": "English courses With Video Playlist",
        "img": "https://www.kidwise.in/wp-content/uploads/2020/04/iStock-950603046.jpg",
        "description": "Your child will get the most out of their English learning experience with a combination of:",
        "duration": 6,
        "cost":40
    },
    {
        "key": 6,
        "course": "Online English courses for adults",
        "img": "https://encrypted-tbn0.gstatic.com/images?q=tbn:ANd9GcTyv1QtYLxzWQ_hWpl9XGjpNv8Y5v_SLY1avw&usqp=CAU",
        "description": "lively classes with a specialist teacher, who will encourage their curiosity and keep them motivated to practise speaking English ",
        "duration": 3,
        "cost":15
    },
    {
        "key": 7,
        "course": "Speak English Course",
        "img": "https://d2jg2pri5bpndu.cloudfront.net/photos/thumbnail/2019/06/11/9212/1500_8ab220ea63ba9917177ba142b7342672.png",
        "description": "interactive independent study, set by your child's teacher to prepare them for the lesson – all in a safe, easy-to-use online .",
        "duration": 8,
        "cost":25
    },
    {
        "key": 8,
        "course": "Hand Written English Course",
        "img": "https://i.ytimg.com/vi/PraiNh8Xep4/maxresdefault.jpg",
        "description": "Primary Plus and Secondary Plus are available in British Council teaching centres and our partner schools in many major cities.",
        "duration": 12,
        "cost":50
    }
]